{"file":"slogan_banner.png","frames":{
"s6":{"x":0,"y":0,"w":591,"h":347,"offX":27,"offY":0,"sourceW":628,"sourceH":352},
"s1":{"x":593,"y":0,"w":615,"h":333,"offX":3,"offY":0,"sourceW":628,"sourceH":352},
"s2":{"x":1210,"y":0,"w":613,"h":333,"offX":5,"offY":0,"sourceW":628,"sourceH":352},
"s3":{"x":593,"y":666,"w":556,"h":326,"offX":66,"offY":3,"sourceW":628,"sourceH":352},
"s4":{"x":593,"y":335,"w":551,"h":329,"offX":67,"offY":0,"sourceW":628,"sourceH":352},
"s5":{"x":0,"y":349,"w":591,"h":347,"offX":27,"offY":0,"sourceW":628,"sourceH":352}}}