{
	"groups":[{
			"keys":"message-btn_png,sec-1_png,sec-2_png,sec-3_png,sec-4_png,sec-foot_png,zp_png,banner_png,buy-btn_png,cake-1_png,cake-2_png,cake-3_png,cake-new_png,group-1_png,group-2_png,hy-title-1_png,hy-title-2_png,message-bg_png",
			"name":"preload"
		}],
	"resources":[
		{
			"name":"message-btn_png",
			"type":"image",
			"url":"message-btn.png"
		},
		{
			"name":"sec-1_png",
			"type":"image",
			"url":"sec-1.png"
		},
		{
			"name":"sec-2_png",
			"type":"image",
			"url":"sec-2.png"
		},
		{
			"name":"sec-3_png",
			"type":"image",
			"url":"sec-3.png"
		},
		{
			"name":"sec-4_png",
			"type":"image",
			"url":"sec-4.png"
		},
		{
			"name":"sec-foot_png",
			"type":"image",
			"url":"sec-foot.png"
		},
		{
			"name":"zp_png",
			"type":"image",
			"url":"zp.png"
		},
		{
			"name":"banner_png",
			"type":"image",
			"url":"banner.png"
		},
		{
			"name":"buy-btn_png",
			"type":"image",
			"url":"buy-btn.png"
		},
		{
			"name":"cake-1_png",
			"type":"image",
			"url":"cake-1.png"
		},
		{
			"name":"cake-2_png",
			"type":"image",
			"url":"cake-2.png"
		},
		{
			"name":"cake-3_png",
			"type":"image",
			"url":"cake-3.png"
		},
		{
			"name":"cake-new_png",
			"type":"image",
			"url":"cake-new.png"
		},
		{
			"name":"group-1_png",
			"type":"image",
			"url":"group-1.png"
		},
		{
			"name":"group-2_png",
			"type":"image",
			"url":"group-2.png"
		},
		{
			"name":"hy-title-1_png",
			"type":"image",
			"url":"hy-title-1.png"
		},
		{
			"name":"hy-title-2_png",
			"type":"image",
			"url":"hy-title-2.png"
		},
		{
			"name":"message-bg_png",
			"type":"image",
			"url":"message-bg.png"
		}
	]
}