{
	"groups":[{
			"keys":"bg_jpg,dis-0_png,dis-1_png,dis-2_png,dis-3_png,father_json,title_png,zhekou-bj_png,zhekou_png",
			"name":"preload"
		}],
	"resources":[
		{
			"name":"bg_jpg",
			"type":"image",
			"url":"fatherDay/bg.jpg"
		},
		{
			"name":"dis-0_png",
			"type":"image",
			"url":"fatherDay/dis-0.png"
		},
		{
			"name":"dis-1_png",
			"type":"image",
			"url":"fatherDay/dis-1.png"
		},
		{
			"name":"dis-2_png",
			"type":"image",
			"url":"fatherDay/dis-2.png"
		},
		{
			"name":"dis-3_png",
			"type":"image",
			"url":"fatherDay/dis-3.png"
		},
		{
			"name":"father_json",
			"subkeys":"father-1,father-10,father-11,father-12,father-13,father-14,father-15,father-16,father-17,father-18,father-19,father-2,father-20,father-21,father-22,father-23,father-3,father-4,father-5,father-6,father-7,father-8,father-9",
			"type":"sheet",
			"url":"fatherDay/father.json"
		},
		{
			"name":"title_png",
			"type":"image",
			"url":"fatherDay/title.png"
		},
		{
			"name":"zhekou-bj_png",
			"type":"image",
			"url":"fatherDay/zhekou-bj.png"
		},
		{
			"name":"zhekou_png",
			"type":"image",
			"url":"fatherDay/zhekou.png"
		}
	]
}